setup.cfg
setup.py
climactic/__init__.py
climactic/case.py
climactic/cli.py
climactic/collector.py
climactic/command.py
climactic/errors.py
climactic/parser.py
climactic/runner.py
climactic/state.py
climactic/suite.py
climactic/tag.py
climactic/utility.py
climactic.egg-info/PKG-INFO
climactic.egg-info/SOURCES.txt
climactic.egg-info/dependency_links.txt
climactic.egg-info/entry_points.txt
climactic.egg-info/requires.txt
climactic.egg-info/top_level.txt
climactic/plugins/__init__.py
climactic/plugins/pytest.py
climactic/test/__init__.py
climactic/test/test_parser.py
climactic/test/test_utility.py