Metadata-Version: 1.1
Name: climactic
Version: 0.3.0
Summary: YAML-based tests for commandline utilities
Home-page: https://github.com/b33j0r/climactic
Author: Brian Jorgensen
Author-email: brian.jorgensen@gmail.com
License: GPLv2
Download-URL: https://github.com/b33j0r/climactic/tarball/v0.3.0
Keywords: testing,cli,yaml,unittest
Platform: UNKNOWN
Classifier: Development Status :: 3 - Alpha
Classifier: Topic :: Utilities
Classifier: Topic :: Software Development :: Testing
Classifier: License :: OSI Approved :: GNU General Public License v2 (GPLv2)
Classifier: Environment :: Console
Classifier: Intended Audience :: Developers
Classifier: Programming Language :: Python :: 3
Classifier: Operating System :: OS Independent
